doc_lsp/__init__.py
doc_lsp/feature.py
doc_lsp/parser.py
doc_lsp-0.1.0.dist-info/METADATA
doc_lsp-0.1.0.dist-info/WHEEL
doc_lsp-0.1.0.dist-info/entry_points.txt
doc_lsp-0.1.0.dist-info/licenses/LICENSE
doc_lsp-0.1.0.dist-info/RECORD
