Metadata-Version: 2.4
Name: doc-lsp
Version: 0.1.0
Summary: Language Server Protocol implementation for loading documentation from separate markdown files
Author-email: Bruno Rocha <rochacbruno@gmail.com>
License: AGPL-3.0-or-later
License-File: LICENSE
Keywords: documentation,hover,language-server,lsp,markdown
Classifier: Development Status :: 3 - Alpha
Classifier: Intended Audience :: Developers
Classifier: License :: OSI Approved :: GNU Affero General Public License v3 or later (AGPLv3+)
Classifier: Programming Language :: Python :: 3
Classifier: Programming Language :: Python :: 3.11
Classifier: Programming Language :: Python :: 3.12
Classifier: Programming Language :: Python :: 3.13
Classifier: Topic :: Software Development :: Documentation
Classifier: Topic :: Text Editors :: Integrated Development Environments (IDE)
Requires-Python: >=3.11
Requires-Dist: pydantic>=2.11.7
Requires-Dist: pygls
Requires-Dist: pyyaml>=6.0.2
Requires-Dist: rich>=14.1.0
